odoo/addons/l10n_eu_oss/README.rst
odoo/addons/l10n_eu_oss/__init__.py
odoo/addons/l10n_eu_oss/__manifest__.py
odoo/addons/l10n_eu_oss/data/oss.tax.rate.csv
odoo/addons/l10n_eu_oss/i18n/l10n_eu_oss.pot
odoo/addons/l10n_eu_oss/models/__init__.py
odoo/addons/l10n_eu_oss/models/account_tax.py
odoo/addons/l10n_eu_oss/models/oss_tax_rate.py
odoo/addons/l10n_eu_oss/readme/CONFIGURE.rst
odoo/addons/l10n_eu_oss/readme/CONTRIBUTORS.rst
odoo/addons/l10n_eu_oss/readme/DESCRIPTION.rst
odoo/addons/l10n_eu_oss/readme/ROADMAP.rst
odoo/addons/l10n_eu_oss/readme/USAGE.rst
odoo/addons/l10n_eu_oss/security/ir.model.access.csv
odoo/addons/l10n_eu_oss/static/description/icon.png
odoo/addons/l10n_eu_oss/static/description/index.html
odoo/addons/l10n_eu_oss/tests/__init__.py
odoo/addons/l10n_eu_oss/tests/test_l10n_eu_oss.py
odoo/addons/l10n_eu_oss/views/res_config_settings.xml
odoo/addons/l10n_eu_oss/wizard/__init__.py
odoo/addons/l10n_eu_oss/wizard/l10n_eu_oss_wizard.py
odoo/addons/l10n_eu_oss/wizard/l10n_eu_oss_wizard.xml
odoo13_addon_l10n_eu_oss-13.0.1.1.1.dist-info/METADATA
odoo13_addon_l10n_eu_oss-13.0.1.1.1.dist-info/WHEEL
odoo13_addon_l10n_eu_oss-13.0.1.1.1.dist-info/top_level.txt
odoo13_addon_l10n_eu_oss-13.0.1.1.1.dist-info/RECORD
